Metadata-Version: 2.0
Name: una-django-cassandra-engine
Version: 3.1.0
Summary: Django Cassandra Engine - the Cassandra backend for Django
Home-page: http://github.com/r4fek/django-cassandra-engine
Author: Rafał Furmański
Author-email: r.furmanski@gmail.com
License: 2-clause BSD
Download-URL: https://github.com/r4fek/django-cassandra-engine/tarball/master
Keywords: django cassandra engine backend driver wrapper database nonrel cqlengine
Platform: UNKNOWN
Classifier: Development Status :: 5 - Production/Stable
Classifier: Environment :: Web Environment
Classifier: Environment :: Plugins
Classifier: Framework :: Django
Classifier: Intended Audience :: Developers
Classifier: License :: OSI Approved :: BSD License
Classifier: Operating System :: OS Independent
Classifier: Programming Language :: Python
Classifier: Programming Language :: Python :: 2.7
Classifier: Programming Language :: Python :: 3.3
Classifier: Programming Language :: Python :: 3.4
Classifier: Topic :: Database
Classifier: Topic :: Internet
Classifier: Topic :: Software Development :: Libraries :: Python Modules
Requires-Dist: Django (<1.10,>=1.9)
Requires-Dist: cassandra-driver (==3.4.1)
Requires-Dist: djangorestframework
Requires-Dist: six (>=1.6)
